<?xml version="1.0" encoding="UTF-8"?>
<record_update table="sysevent_register">
    <sysevent_register action="INSERT_OR_UPDATE">
        <description>Used to queue email notifications for Recurrent Reservations about to expire.</description>
        <event_name>x_lsmcb_fm.recurrent.reservation.expires</event_name>
        <fired_by>Shecule Job: FM - Recurrent Reservation Pre-expiration Notification</fired_by>
        <queue/>
        <suffix>recurrent.reservation.expires</suffix>
        <sys_class_name>sysevent_register</sys_class_name>
        <sys_created_by>laura.schuch</sys_created_by>
        <sys_created_on>2016-10-06 07:52:34</sys_created_on>
        <sys_id>c2f506a10fd6ea0011bec3ace1050ef4</sys_id>
        <sys_mod_count>2</sys_mod_count>
        <sys_name>x_lsmcb_fm.recurrent.reservation.expires</sys_name>
        <sys_package display_value="Facility Management Accelerator" source="x_lsmcb_fm">e080882f0f9d224011bec3ace1050ee5</sys_package>
        <sys_policy/>
        <sys_scope display_value="Facility Management Accelerator">e080882f0f9d224011bec3ace1050ee5</sys_scope>
        <sys_update_name>sysevent_register_c2f506a10fd6ea0011bec3ace1050ef4</sys_update_name>
        <sys_updated_by>david.neves</sys_updated_by>
        <sys_updated_on>2018-07-16 13:57:41</sys_updated_on>
        <table>x_lsmcb_fm_room_reservation</table>
    </sysevent_register>
</record_update>
